server/__init__.py
server/alembic.ini
server/application.py
server/config.py
server/create_db.sh
server/gui/__init__.py
server/gui/clients_window.py
server/gui/generate_server_ui.sh
server/gui/history_window.py
server/gui/main_window.py
server/gui/server_gui.ui
server/gui/server_gui_clients.ui
server/gui/server_gui_history.ui
server/logger_conf.py
server/migrations/README
server/migrations/env.py
server/migrations/script.py.mako
server/migrations/versions/2023-01-04_07-48_bdb20895b216_initial.py
server/model.py
server/run_server_cli.py
server/run_server_gui.py
server/storage.py
server/transport.py
gb_pychat_server-0.1.2.dist-info/entry_points.txt
gb_pychat_server-0.1.2.dist-info/WHEEL
gb_pychat_server-0.1.2.dist-info/METADATA
gb_pychat_server-0.1.2.dist-info/RECORD
