Metadata-Version: 2.1
Name: gb-pychat-server
Version: 0.1.2
Summary: 
License: MIT
Author: DashViolin
Author-email: mymail@srv.org
Requires-Python: >=3.10,<4.0
Classifier: License :: OSI Approved :: MIT License
Classifier: Programming Language :: Python :: 3
Classifier: Programming Language :: Python :: 3.10
Requires-Dist: PyQt6 (>=6.4.0,<7.0.0)
Requires-Dist: SQLAlchemy (>=1.4.44,<2.0.0)
Requires-Dist: alembic (>=1.8.1,<2.0.0)
Requires-Dist: gb-pychat-common (>=0.1.0,<0.2.0)
